{
    "Ar36": {
        "error": 0.0023128775895286152, 
        "fit": "parabolic", 
        "value": 0.025175874891719761
    }, 
    "Ar37": {
        "error": 0.13816709915431014, 
        "fit": "linear", 
        "value": -0.010767073515690657
    }, 
    "Ar38": {
        "error": 0.1390340244957218, 
        "fit": "linear", 
        "value": 0.070871513929175844
    }, 
    "Ar39": {
        "error": 0.070421855044148551, 
        "fit": "parabolic", 
        "value": 12.154474013643689
    }, 
    "Ar40": {
        "error": 0.58280630515195431, 
        "fit": "parabolic", 
        "value": 2203.7762544887692
    }, 
    "Ar41": {
        "error": 0.1214244548041032, 
        "fit": "average_SEM", 
        "value": -0.034458548157872429
    }
}